pimcp3008/__init__.py
pimcp3008/pimcp3008.py
pimcp3008-1.0.1.dist-info/DESCRIPTION.rst
pimcp3008-1.0.1.dist-info/METADATA
pimcp3008-1.0.1.dist-info/RECORD
pimcp3008-1.0.1.dist-info/WHEEL
pimcp3008-1.0.1.dist-info/metadata.json
pimcp3008-1.0.1.dist-info/top_level.txt
