Metadata-Version: 2.0
Name: pimcp3008
Version: 1.0.1
Summary: To use MCP3008 with pigpio.
Home-page: https://github.com/Langur/pimcp3008
Author: Akihisa ONODA
Author-email: akihisa.onoda@osarusystem.com
License: MIT
Keywords: pimcp3008 mcp3004 mcp3008 pigpio adc analog-to-digital spi
Platform: UNKNOWN
Classifier: License :: OSI Approved :: MIT License
Classifier: Programming Language :: Python :: 3
Classifier: Programming Language :: Python :: 3.7
Requires-Dist: pigpio
